{"version":"1","name":"Kolthar al Magus","race":"Gharu'ndim","gender":"Male","level":235,"allegiance_name":"A group of normal humans","rank":2,"followers":7,"server":"WintersEbb","server_population":103,"deaths":178,"birth":"1/27/2001 10:53:22 PM","total_xp":87890398105,"unassigned_xp":5134927771,"skill_credits":15,"luminance_earned":6169,"luminance_total":1500000,"attribs":{"strength":{"name":"Strength","base":200,"creation":10},"endurance":{"name":"Endurance","base":200,"creation":10},"quickness":{"name":"Quickness","base":200,"creation":10},"coordination":{"name":"Coordination","base":290,"creation":100},"focus":{"name":"Focus","base":290,"creation":100},"self":{"name":"Self","base":290,"creation":100}},"vitals":{"health":{"name":"Health","base":296},"stamina":{"name":"Stamina","base":396},"mana":{"name":"Mana","base":486}},"skills":{"melee_defense":{"name":"melee_defense","base":399,"training":"Specialized"},"missile_defense":{"name":"missile_defense","base":98,"training":"Untrained"},"arcane_lore":{"name":"arcane_lore","base":305,"training":"Trained"},"magic_defense":{"name":"magic_defense","base":285,"training":"Trained"},"mana_conversion":{"name":"mana_conversion","base":305,"training":"Trained"},"item_tinkering":{"name":"item_tinkering","base":290,"training":"Untrained"},"assess_person":{"name":"assess_person","base":0,"training":"Untrained"},"deception":{"name":"deception","base":0,"training":"Untrained"},"healing":{"name":"healing","base":0,"training":"Unusable"},"jump":{"name":"jump","base":385,"training":"Trained"},"lockpick":{"name":"lockpick","base":0,"training":"Unusable"},"run":{"name":"run","base":406,"training":"Trained"},"assess_creature":{"name":"assess_creature","base":0,"training":"Untrained"},"weapon_tinkering":{"name":"weapon_tinkering","base":245,"training":"Untrained"},"armor_tinkering":{"name":"armor_tinkering","base":245,"training":"Untrained"},"magic_item_tinkering":{"name":"magic_item_tinkering","base":290,"training":"Untrained"},"creature_enchantment":{"name":"creature_enchantment","base":353,"training":"Trained"},"item_enchantment":{"name":"item_enchantment","base":353,"training":"Trained"},"life_magic":{"name":"life_magic","base":353,"training":"Trained"},"war_magic":{"name":"war_magic","base":381,"training":"Specialized"},"leadership":{"name":"leadership","base":0,"training":"Untrained"},"loyalty":{"name":"loyalty","base":208,"training":"Trained"},"fletching":{"name":"fletching","base":0,"training":"Unusable"},"alchemy":{"name":"alchemy","base":0,"training":"Unusable"},"cooking":{"name":"cooking","base":0,"training":"Unusable"},"salvaging":{"name":"salvaging","base":150,"training":"Trained"},"two_handed_combat":{"name":"two_handed_combat","base":163,"training":"Untrained"},"void_magic":{"name":"void_magic","base":0,"training":"Unusable"},"heavy_weapons":{"name":"heavy_weapons","base":163,"training":"Untrained"},"light_weapons":{"name":"light_weapons","base":163,"training":"Untrained"},"finesse_weapons":{"name":"finesse_weapons","base":163,"training":"Untrained"},"missile_weapons":{"name":"missile_weapons","base":145,"training":"Untrained"},"shield":{"name":"shield","base":245,"training":"Untrained"},"dual_wield":{"name":"dual_wield","base":193,"training":"Untrained"},"recklessness":{"name":"recklessness","base":0,"training":"Unusable"},"sneak_attack":{"name":"sneak_attack","base":0,"training":"Unusable"},"dirty_fighting":{"name":"dirty_fighting","base":0,"training":"Unusable"},"summoning":{"name":"summoning","base":0,"training":"Unusable"}},"monarch":{"name":"Crafty Simulacrum","race":4,"rank":8,"gender":2,"followers":1105},"patron":{"name":"Kolthar","race":1,"rank":2,"gender":1},"vassals":[{"name":"Kolthar Jones","race":2,"rank":1,"gender":1},{"name":"Kolthar's Rares","race":2,"rank":1,"gender":2},{"name":"Xiao Hu Luo","race":3,"rank":1,"gender":1},{"name":"Sierra","race":1,"rank":1,"gender":2},{"name":"Rheingeld","race":3,"rank":1,"gender":1},{"name":"Kolth's Yoroi","race":8,"rank":1,"gender":1},{"name":"Kolth's Heavy Armor","race":8,"rank":1,"gender":1}],"current_title":29,"titles":[713,69,36,56,74,708,60,29,66],"properties":{"384":0,"192":196,"386":0,"322":7,"387":0,"323":0,"388":0,"132":7,"389":0,"390":0,"326":1,"199":1153562863,"329":0,"330":0,"331":0,"139":233,"333":0,"334":0,"335":0,"336":0,"338":0,"339":0,"340":0,"342":0,"343":0,"344":0,"281":4,"350":0,"351":0,"289":1,"354":7,"355":12,"231":3,"360":0,"40":1,"361":0,"365":0,"47":0,"370":0,"371":0,"307":0,"372":0,"308":0,"373":0,"374":0,"375":0,"376":0,"312":0,"377":0,"313":0,"378":0,"314":0,"379":0,"315":0,"316":0,"381":0,"317":0,"382":0,"318":0,"383":0}}